Metadata-Version: 2.1
Name: hausschrat-nextcloud-s3
Version: 1
Summary: hausschrat mixed vendor example
Home-page: https://git.osuv.de/m/hausschrat
Author: Markus Bergholz
Author-email: git@osuv.de  
License: WTFPL
Platform: UNKNOWN
